imgsearch/__init__.py
imgsearch-2021.5.25.dist-info/LICENSE
imgsearch-2021.5.25.dist-info/METADATA
imgsearch-2021.5.25.dist-info/WHEEL
imgsearch-2021.5.25.dist-info/top_level.txt
imgsearch-2021.5.25.dist-info/RECORD
