Metadata-Version: 2.1
Name: imgsearch
Version: 2021.5.25
Summary: A simple image search
Home-page: https://github.com/gamingdy/image-search-python
Author: Gamingdy
License: UNKNOWN
Project-URL: Bug Tracker, https://github.com/gamingdy/image-search-python/issues
Platform: UNKNOWN
Classifier: Programming Language :: Python :: 3
Classifier: License :: OSI Approved :: MIT License
Classifier: Operating System :: OS Independent
Requires-Python: >=3.6
License-File: LICENSE
